<?xml version="1.0" encoding="utf-8"?>
<odoo>
    <data noupdate="1">
        <record id="menu_sale_order_web" model="website.menu">
            <field name="name">Branch Order</field>
            <field name="url">/sale</field>
            <field name="parent_id" ref="website.main_menu"/>
            <field name="sequence" type="int">32</field>
        </record>

    	<record id="partner_central_kitchen" model="res.partner">
            <field name="name">Central Kitchen</field>
            <field name="supplier">True</field>
            <field name="customer">False</field>
            <field name="is_central_kitchen">True</field>
        </record>
    </data>
</odoo>